requests_from_file/__init__.py
requests_from_file-2.0.dist-info/DESCRIPTION.rst
requests_from_file-2.0.dist-info/METADATA
requests_from_file-2.0.dist-info/RECORD
requests_from_file-2.0.dist-info/WHEEL
requests_from_file-2.0.dist-info/metadata.json
requests_from_file-2.0.dist-info/top_level.txt
