Metadata-Version: 2.0
Name: requests-from-file
Version: 2.0
Summary: create requests params from file,file is created by Firefox Header
Home-page: https://github.com/zhangtao103239/requests_from_file
Author: zhangtao103239
Author-email: zhangtao103239@163.com
License: UNKNOWN
Platform: UNKNOWN
Classifier: Programming Language :: Python :: 3
Classifier: License :: OSI Approved :: MIT License
Classifier: Operating System :: OS Independent
Requires-Dist: requests
